{
  "cohort_icu_encounters": null,
  "cohort_sepsis_patients": null,
  "n_transitions": null,
  "state_dim": null,
  "split_counts": {
    "train": 414522,
    "val": 88812,
    "test": 88848
  },
  "behavior_episode_return": 0.6855753646677472,
  "bc_wis_mean": 0.5640081939433821,
  "bc_wis_ci95": [
    -0.9685610900129464,
    0.9999995148979495
  ],
  "cql_wis_mean": 0.7859551638174903,
  "cql_wis_ci95": [
    0.7666980391017969,
    0.8053712276161398
  ],
  "eval_split": "test",
  "n_episodes_eval": 4936,
  "behavior_survival_proxy": 0.8427876823338736,
  "bc_survival_proxy": 0.782004096971691,
  "cql_survival_proxy": 0.8929775819087451,
  "value_survival_corr": 0.9999999999999999,
  "action_distribution_divergence": {},
  "top_features_rf_proxy": [
    {
      "feature": "f5",
      "importance": 0.2344686340298747
    },
    {
      "feature": "f4",
      "importance": 0.22397314317797043
    },
    {
      "feature": "f6",
      "importance": 0.1898036742135982
    },
    {
      "feature": "f0",
      "importance": 0.09447151985619796
    },
    {
      "feature": "f1",
      "importance": 0.09012237718937204
    },
    {
      "feature": "f2",
      "importance": 0.07814390692865056
    },
    {
      "feature": "f3",
      "importance": 0.07147589833692701
    },
    {
      "feature": "f7",
      "importance": 0.017540846267409135
    }
  ],
  "figures": {
    "fig2_training_objective_curves": "report\\generated\\figures\\minimal\\fig2_training_objective_curves.png",
    "fig4_feature_importance_rf_proxy": "report\\generated\\figures\\minimal\\fig4_feature_importance_rf_proxy.png",
    "fig5_action_distribution_comparison": null,
    "fig6_return_survival_relationship": "report\\generated\\figures\\minimal\\fig6_return_survival_relationship.png",
    "fig7_final_survival_comparison": "report\\generated\\figures\\minimal\\fig7_final_survival_comparison.png"
  },
  "recommended_additional_metrics": [
    "ESS (effective sample size) per policy",
    "Off-support action rate",
    "Binning-interval ablation (1/2/4/6/8h)",
    "Subgroup policy value by lactate/shock severity"
  ],
  "icu_sepsis": {
    "n_episodes": 50,
    "n_transitions": 359,
    "state_dim": 716,
    "avg_episode_return": 0.72,
    "behavior_episode_return": 0.75,
    "bc_wis_mean": 0.7717240820147546,
    "bc_wis_ci95": [
      0.4288945767841774,
      1.0
    ],
    "cql_wis_mean": 0.7858448066670896,
    "cql_wis_ci95": [
      0.4975492982675797,
      1.0
    ],
    "eval_split": "test",
    "n_episodes_eval": 8
  }
}